graphqldb/__init__.py
graphqldb/adapter.py
graphqldb/db_engine_specs.py
graphqldb/dialect.py
graphqldb/lib.py
graphqldb/types.py
sqlalchemy_graphqlapi-0.0.1.dev5.dist-info/LICENSE
sqlalchemy_graphqlapi-0.0.1.dev5.dist-info/METADATA
sqlalchemy_graphqlapi-0.0.1.dev5.dist-info/WHEEL
sqlalchemy_graphqlapi-0.0.1.dev5.dist-info/entry_points.txt
sqlalchemy_graphqlapi-0.0.1.dev5.dist-info/top_level.txt
sqlalchemy_graphqlapi-0.0.1.dev5.dist-info/RECORD
