Metadata-Version: 2.1
Name: sqlalchemy-graphqlapi
Version: 0.0.1.dev5
Summary: Python DB-API and SQLAlchemy interface for GraphQL APIs.
Home-page: https://github.com/cancan101/graphql-db-api
Author: Alex Rothberg
Author-email: agrothberg@gmail.com
License: MIT
Classifier: Development Status :: 2 - Pre-Alpha
Classifier: License :: OSI Approved :: MIT License
Classifier: Programming Language :: Python
Classifier: Programming Language :: Python :: 3.8
Classifier: Programming Language :: Python :: 3.9
Classifier: Programming Language :: Python :: 3.10
Classifier: Programming Language :: Python :: 3.11
Classifier: Programming Language :: Python :: Implementation :: CPython
License-File: LICENSE
Requires-Dist: shillelagh >=1.2.0
Requires-Dist: requests >=2.31.0
